connect/reports/__init__.py
connect/reports/constants.py
connect/reports/datamodels.py
connect/reports/parser.py
connect/reports/renderers/__init__.py
connect/reports/renderers/base.py
connect/reports/renderers/csv.py
connect/reports/renderers/j2.py
connect/reports/renderers/json.py
connect/reports/renderers/pdf.py
connect/reports/renderers/registry.py
connect/reports/renderers/utils.py
connect/reports/renderers/xlsx.py
connect/reports/schemas/reports_schema.json
connect/reports/validator.py
connect_reports_core-34.0.dist-info/LICENSE
connect_reports_core-34.0.dist-info/METADATA
connect_reports_core-34.0.dist-info/WHEEL
connect_reports_core-34.0.dist-info/RECORD
