Metadata-Version: 2.1
Name: connect-reports-core
Version: 34.0
Summary: Connect Reports Core
Home-page: https://connect.cloudblue.com
License: Apache-2.0
Author: CloudBlue LLC
Requires-Python: >=3.9,<4
Classifier: Development Status :: 5 - Production/Stable
Classifier: Environment :: Console
Classifier: Intended Audience :: Developers
Classifier: License :: OSI Approved :: Apache Software License
Classifier: Operating System :: OS Independent
Classifier: Programming Language :: Python :: 3
Classifier: Programming Language :: Python :: 3.9
Classifier: Programming Language :: Python :: 3.10
Classifier: Programming Language :: Python :: 3.11
Classifier: Programming Language :: Python :: 3.12
Classifier: Programming Language :: Python :: 3.13
Classifier: Topic :: Software Development :: Libraries
Classifier: Topic :: Utilities
Requires-Dist: Jinja2 (>=2,<4)
Requires-Dist: WeasyPrint (>=59,<64)
Requires-Dist: jsonschema (>=3,<5)
Requires-Dist: kaleido (>=0.4,<1)
Requires-Dist: lxml (>=4.9)
Requires-Dist: openpyxl (>=2.5.14)
Requires-Dist: orjson (>=3.5.2,<4)
Requires-Dist: plotly (>=5.9.0,<6)
Requires-Dist: pytz
Project-URL: Repository, https://github.com/cloudblue/connect-reports-core
